pygologin/__init__.py
pygologin/__meta__.py
pygologin/exceptions.py
pygologin/gologin.py
pygologin/cookiesManager/__init__.py
pygologin/cookiesManager/cookiesManager.py
pygologin/extensionsManager/__init__.py
pygologin/extensionsManager/extensionsManager.py
pygologin-0.1.9.dist-info/METADATA
pygologin-0.1.9.dist-info/WHEEL
pygologin-0.1.9.dist-info/licenses/LICENSE
pygologin-0.1.9.dist-info/RECORD
