Metadata-Version: 2.4
Name: pygologin
Version: 0.1.9
Summary: Not official GoLogin python package
Project-URL: Homepage, https://github.com/at146/pygologin
Project-URL: Repository, https://github.com/at146/pygologin
Project-URL: Issues, https://github.com/at146/pygologin/issues
Author-email: Alex Tarasov <at146@ya.ru>
Maintainer-email: Alex Tarasov <at146@ya.ru>
License-Expression: MIT
License-File: LICENSE
Keywords: api,gologin
Classifier: License :: OSI Approved :: MIT License
Classifier: Operating System :: OS Independent
Classifier: Programming Language :: Python :: 3
Requires-Python: >=3.8
Requires-Dist: psutil<7.1,>=6.0
Requires-Dist: requests<3,>=2
Provides-Extra: dev
Requires-Dist: mypy<1.16.0,>=1.11.2; extra == 'dev'
Requires-Dist: pre-commit<4.0,>=3.5.0; extra == 'dev'
Requires-Dist: ruff~=0.11.0; extra == 'dev'
Requires-Dist: types-psutil<7.0.1.0,>=6.0.0.20240901; extra == 'dev'
Requires-Dist: types-requests~=2.32.0.20240905; extra == 'dev'
Provides-Extra: test
Requires-Dist: pytest~=8.3.2; extra == 'test'
